{
	 "clientPrefab":"Priest",
     "moveSpeed":6,
	 "health":90,
	 "collision":1,
	 "heroType":0,
	 "defaultBuffs":
	 [
		{
			"buffType":5,
			"buffEffect":2,
			"buffTime":0
		}
	 ],
	 "skills":
	 [
	 	{
			"clientPrefab":"Poison",
			"moveSpeed":12,
			"collision":2,
			"effect":2,
			"effectTime":12,
			"effectType":2,
			"cooldown":8,
			"casttime":0,
			"life":2,
			"hitAndDestroy":true,
			"hitContinous":false,
			"skillType":0,
			"activeAfter":0,
			"botsDecideChance":80
		},
		{
			"clientPrefab":"Heal",
			"moveSpeed":0,
			"collision":5,
			"effect":4,
			"effectType":1,
			"cooldown":22,
			"casttime":1,
			"life":5,
			"hitAndDestroy":false,
			"hitContinous":true,
			"skillType":1,
			"activeAfter":0,
			"botsDecideChance":30
		},
		{
			"clientPrefab":"Stun",
			"moveSpeed":0,
			"collision":5,
			"effect":20,
			"effectTime":2,
			"effectType":3,
			"cooldown":9,
			"casttime":1.5,
			"life":3,
			"hitAndDestroy":false,
			"hitContinous":true,
			"skillType":1,
			"activeAfter":0,
			"botsDecideChance":100
		}
	 ],
	 "levels":
	 [
		{
			"level":2,
			"Percent_effect":10,
		    "Percent_cooldown":20,
			"Percent_fastercast":20
		},
		{
			"level":3,
			"Percent_effect":10,
			"Percent_movespeed":10,
		    "Percent_cooldown":20,
			"Percent_fastercast":20
		},
		{
			"level":5,
			"Percent_effect":20,
			"Percent_fastercast":25,
			"Percent_movespeed":10,
		    "Percent_cooldown":25
		}
	 ]
}